{
  "project_info": {
    "project_number": "464192368138",
    "project_id": "jeevibe",
    "storage_bucket": "jeevibe.firebasestorage.app"
  },
  "client": [
    {
      "client_info": {
        "mobilesdk_app_id": "1:464192368138:android:9d132478d3d9a82e9679f3",
        "android_client_info": {
          "package_name": "com.jeevibe.jeevibe_mobile"
        }
      },
      "oauth_client": [],
      "api_key": [
        {
          "current_key": "AIzaSyDcXazgUQe2MAp1xAtEtGC-OXhF-Y9UYjc"
        }
      ],
      "services": {
        "appinvite_service": {
          "other_platform_oauth_client": []
        }
      }
    }
  ],
  "configuration_version": "1"
}